epypen/__init__.py
epypen/conversions.py
epypen/exceptions.py
epypen/main.py
epypen/utils.py
epypen-1.0.4.dist-info/METADATA
epypen-1.0.4.dist-info/WHEEL
epypen-1.0.4.dist-info/top_level.txt
epypen-1.0.4.dist-info/RECORD
