Metadata-Version: 2.4
Name: epypen
Version: 1.0.4
Summary: epypen is a lightweight translation decorator that bridges the gap between raw Python objects and type-annotated data.
License: GPL-3.0
Project-URL: Homepage, https://github.com/avivgood/epypen
Project-URL: Documentation, https://github.com/avivgood/epypen/blob/main/README.md
Project-URL: Repository, https://github.com/avivgood/epypen.git
Project-URL: Issues, https://github.com/avivgood/epypen/issues
Classifier: Development Status :: 5 - Production/Stable
Classifier: Natural Language :: English
Classifier: Operating System :: OS Independent
Classifier: Intended Audience :: Developers
Classifier: Topic :: Software Development :: Libraries :: Python Modules
Classifier: Typing :: Typed
Classifier: License :: OSI Approved :: GNU General Public License v3 (GPLv3)
Classifier: Programming Language :: Python :: 3
Classifier: Programming Language :: Python :: 3.8
Classifier: Programming Language :: Python :: 3.9
Classifier: Programming Language :: Python :: 3.10
Classifier: Programming Language :: Python :: 3.11
Classifier: Programming Language :: Python :: 3.12
Classifier: Programming Language :: Python :: 3.13
Requires-Python: >=3.8
Requires-Dist: pydantic<3.0.0
Requires-Dist: typing-extensions>=4.0.0
